{
	"variables": [],
	"info": {
		"name": "shopCart",
		"_postman_id": "9bba73e4-b27c-1d4f-e01a-16cbe5ffb660",
		"description": "",
		"schema": "https://schema.getpostman.com/json/collection/v2.0.0/collection.json"
	},
	"item": [
		{
			"name": "add",
			"request": {
				"url": "localhost:8080/cart/add",
				"method": "POST",
				"header": [
					{
						"key": "Content-Type",
						"value": "application/json",
						"description": ""
					}
				],
				"body": {
					"mode": "raw",
					"raw": "{\n\t\"item\": {\n\t\t\"id\": 1,\n\t\t\"name\": \"product1\"\n\t}\n}"
				},
				"description": ""
			},
			"response": []
		},
		{
			"name": "list",
			"request": {
				"url": "localhost:8080/cart/list",
				"method": "GET",
				"header": [],
				"body": {},
				"description": ""
			},
			"response": []
		}
	]
}